LICENSE
MANIFEST.in
README.md
setup.cfg
setup.py
efjdown/efjdown.py
efjdown.egg-info/PKG-INFO
efjdown.egg-info/SOURCES.txt
efjdown.egg-info/dependency_links.txt
efjdown.egg-info/entry_points.txt
efjdown.egg-info/requires.txt
efjdown.egg-info/top_level.txt