Metadata-Version: 2.1
Name: efjdown
Version: 1.1.1
License-File: LICENSE
